sparams/__init__.py
sparams/sparams.py
sparams-5.0.0.dist-info/METADATA
sparams-5.0.0.dist-info/WHEEL
sparams-5.0.0.dist-info/top_level.txt
sparams-5.0.0.dist-info/RECORD
