Metadata-Version: 2.4
Name: sparams
Version: 5.0.0
Summary: A simple config watcher 
Author: PAT
Requires-Python: >=3.8
Requires-Dist: watchdog
Requires-Dist: pyyaml
Requires-Dist: numpy
Dynamic: author
Dynamic: description
Dynamic: description-content-type
Dynamic: requires-dist
Dynamic: requires-python
Dynamic: summary
